{
  "notification": {
    "getInterruptionFilterFromListener": {
      "ordered_iterations": [
        {
          "execution_outcome": {
            "returns": false,
            "output": null
          },
          "pid_info": null,
          "uid_info": null,
          "uid_works": true,
          "exception": {
            "is_security": false,
            "data": null
          },
          "appops_operations": [],
          "to_instrument": [],
          "stacktrace": [],
          "data": {
            "appOps": [],
            "methods": [],
            "permissions": [],
            "pid": null,
            "uid": null,
            "userId": null,
            "user_restrictions": [],
            "parameters_hash": "b3969070da5a5043d3f83bababde34d6",
            "ignored_permissions": []
          }
        },
        {
          "execution_outcome": {
            "returns": true,
            "output": "1",
            "exception": "null"
          },
          "pid_info": null,
          "uid_info": null,
          "uid_works": true,
          "exception": {
            "is_security": false,
            "data": null
          },
          "appops_operations": [],
          "to_instrument": [],
          "data": {
            "appOps": [],
            "methods": [],
            "permissions": [],
            "pid": null,
            "uid": null,
            "userId": null,
            "user_restrictions": [],
            "parameters_hash": "b3969070da5a5043d3f83bababde34d6",
            "ignored_permissions": []
          },
          "stacktrace": []
        }
      ]
    }
  }
}